slack_asyncio/__init__.py
slack_asyncio/api.py
slack_asyncio/bot.py
slack_asyncio-0.0.1.dist-info/DESCRIPTION.rst
slack_asyncio-0.0.1.dist-info/METADATA
slack_asyncio-0.0.1.dist-info/RECORD
slack_asyncio-0.0.1.dist-info/WHEEL
slack_asyncio-0.0.1.dist-info/metadata.json
slack_asyncio-0.0.1.dist-info/top_level.txt
